spanned_toml/__init__.py
spanned_toml/_parser.py
spanned_toml/_re.py
spanned_toml/_types.py
spanned_toml/py.typed
spanned_toml-2.0.1.1.dist-info/LICENSE
spanned_toml-2.0.1.1.dist-info/WHEEL
spanned_toml-2.0.1.1.dist-info/METADATA
spanned_toml-2.0.1.1.dist-info/RECORD
