Metadata-Version: 2.1
Name: spanned-toml
Version: 2.0.1.1
Summary: A lil' TOML parser, but with span
Keywords: toml,spanned,tomli
Author-email: Jérome Eertmans <jeertmans@icloud.com>, Taneli Hukkinen <hukkin@users.noreply.github.com>
Requires-Python: >=3.7
Classifier: License :: OSI Approved :: MIT License
Classifier: Operating System :: MacOS
Classifier: Operating System :: Microsoft :: Windows
Classifier: Operating System :: POSIX :: Linux
Classifier: Programming Language :: Python :: 3 :: Only
Classifier: Programming Language :: Python :: Implementation :: CPython
Classifier: Programming Language :: Python :: Implementation :: PyPy
Classifier: Topic :: Software Development :: Libraries :: Python Modules
Classifier: Typing :: Typed
Project-URL: Changelog, https://github.com/jeertmans/spanned-toml/blob/master/CHANGELOG.md
Project-URL: Homepage, https://github.com/jeertmans/spanned-toml
